index_eab/__init__.py
index_eab/eab_utils/__init__.py
index_eab/eab_utils/candidate_generation.py
index_eab/eab_utils/common_utils.py
index_eab/eab_utils/cost_evaluation.py
index_eab/eab_utils/database_connector.py
index_eab/eab_utils/index.py
index_eab/eab_utils/postgres_dbms.py
index_eab/eab_utils/what_if_index_creation.py
index_eab/eab_utils/workload.py
index_eab/index_advisor/__init__.py
index_eab/index_advisor/drop_algorithm.py
index_eab/index_advisor/extend_algorithm.py
index_eab/index_advisor/selection_algorithm.py
index_eab-0.1.0.dist-info/LICENSE
index_eab-0.1.0.dist-info/METADATA
index_eab-0.1.0.dist-info/WHEEL
index_eab-0.1.0.dist-info/top_level.txt
index_eab-0.1.0.dist-info/RECORD
