Metadata-Version: 2.1
Name: index-eab
Version: 0.1.0
Summary: This is a simplified package for the "Index Advisor (EA&B)" project.
Home-page: https://github.com/
Author: Belief
Author-email: 
License: MIT
Platform: UNKNOWN
Classifier: License :: OSI Approved :: MIT License
Classifier: Programming Language :: Python
Classifier: Programming Language :: Python :: 3
Classifier: Programming Language :: Python :: 3.7
Classifier: Programming Language :: Python :: Implementation :: CPython
Classifier: Programming Language :: Python :: Implementation :: PyPy
Requires-Python: >=3.7.0
